l2_r0prover-0.2.0.dist-info/METADATA
l2_r0prover-0.2.0.dist-info/WHEEL
l2_r0prover/__init__.py
l2_r0prover/l2_r0prover.cpython-312-darwin.so
l2_r0prover-0.2.0.dist-info/RECORD
