Metadata-Version: 2.1
Name: l2_r0prover
Version: 0.2.0
Classifier: Environment :: GPU
Classifier: Programming Language :: Rust
Classifier: Intended Audience :: Developers
Classifier: Intended Audience :: Science/Research
Classifier: Intended Audience :: System Administrators
Classifier: Operating System :: MacOS
Classifier: Operating System :: POSIX :: Linux
Classifier: Programming Language :: Python :: Implementation :: CPython
Classifier: Programming Language :: Python :: Implementation :: PyPy
Classifier: License :: OSI Approved :: MIT License
Classifier: License :: OSI Approved :: Apache Software License
Classifier: Topic :: Security :: Cryptography
Summary: A Python wrapper for RISC Zero prover
Author-email: Weikeng Chen <weikeng.chen@l2iterative.com>
Requires-Python: >=3.7
Project-URL: Homepage, https://github.com/l2iterative/r0prover-python/
